say_it_to_my_face.py
say_it_to_my_face-1.0.dist-info/DESCRIPTION.rst
say_it_to_my_face-1.0.dist-info/METADATA
say_it_to_my_face-1.0.dist-info/metadata.json
say_it_to_my_face-1.0.dist-info/RECORD
say_it_to_my_face-1.0.dist-info/top_level.txt
say_it_to_my_face-1.0.dist-info/WHEEL
